README.md
setup.py
ros1_fuzzer/__init__.py
ros1_fuzzer/process_handling.py
ros1_fuzzer/ros_basic_strategies.py
ros1_fuzzer/ros_commons.py
ros1_fuzzer/ros_fuzzer.py
ros1_fuzzer/test.py
ros1_fuzzer.egg-info/PKG-INFO
ros1_fuzzer.egg-info/SOURCES.txt
ros1_fuzzer.egg-info/dependency_links.txt
ros1_fuzzer.egg-info/entry_points.txt
ros1_fuzzer.egg-info/requires.txt
ros1_fuzzer.egg-info/top_level.txt