Metadata-Version: 1.0
Name: ros1-fuzzer
Version: 1.0.0
Summary: A ROS subscriber fuzzing tool for ROS systems
Home-page: https://www.aliasrobotics.com
Author: Alias Robotics
Author-email: contact@aliasrobotics.com
License: GPLv2
Keywords: network,fuzzing,ros
Platform: UNKNOWN
